setup.cfg
setup.py
qualified/__init__.py
qualified/_version.py
qualified/qualified.py
qualified.egg-info/PKG-INFO
qualified.egg-info/SOURCES.txt
qualified.egg-info/dependency_links.txt
qualified.egg-info/top_level.txt